amiquizvoucher-0.1.dist-info/licenses/LICENSE
quiz_voucher/__init__.py
quiz_voucher/voucher.py
amiquizvoucher-0.1.dist-info/METADATA
amiquizvoucher-0.1.dist-info/WHEEL
amiquizvoucher-0.1.dist-info/top_level.txt
amiquizvoucher-0.1.dist-info/RECORD
